pipenv_tools/__init__.py
pipenv_tools/__version__.py
pipenv_tools/core.py
pipenv_tools-0.0.1.dist-info/DESCRIPTION.rst
pipenv_tools-0.0.1.dist-info/METADATA
pipenv_tools-0.0.1.dist-info/RECORD
pipenv_tools-0.0.1.dist-info/WHEEL
pipenv_tools-0.0.1.dist-info/metadata.json
pipenv_tools-0.0.1.dist-info/top_level.txt
