Metadata-Version: 2.0
Name: pipenv-tools
Version: 0.0.1
Summary: The missing tools for pipenv.
Home-page: https://github.com/rochacbruno/pipenv_tools
Author: Bruno Rocha
Author-email: rochacbruno@gmail.com
License: MIT
Platform: UNKNOWN
Classifier: License :: OSI Approved :: MIT License
Classifier: Programming Language :: Python
Classifier: Programming Language :: Python :: 2.6
Classifier: Programming Language :: Python :: 2.7
Classifier: Programming Language :: Python :: 3
Classifier: Programming Language :: Python :: 3.3
Classifier: Programming Language :: Python :: 3.4
Classifier: Programming Language :: Python :: 3.5
Classifier: Programming Language :: Python :: 3.6
Classifier: Programming Language :: Python :: Implementation :: CPython
Classifier: Programming Language :: Python :: Implementation :: PyPy
Requires-Dist: pipenv
Requires-Dist: twine
